test/__init__.py
test/bug_6_tests.py
test/console_me_tests.py
test/context_meta_tests.py
test/context_tests.py
test/data_context_tests.py
test/ha_pipeline_tests.py
test/package_tests.py
test/pipeline_lock_tests.py
test/pipeline_metrics_tests.py
test/pipeline_scheduler_tests.py
test/pipeline_tests.py
test/pipeline_versioning_tests.py
test/redis_pipeline_lock_tests.py
test/sequence_tests.py
test/standalone_pipeline_tests.py
watergrid/__init__.py
watergrid/_version.py
watergrid/__pycache__/__init__.cpython-310.pyc
watergrid/__pycache__/_version.cpython-310.pyc
watergrid/context/__init__.py
watergrid/context/context_metadata.py
watergrid/context/data_context.py
watergrid/context/output_mode.py
watergrid/locks/MockPipelineLock.py
watergrid/locks/PipelineLock.py
watergrid/locks/RedisPipelineLock.py
watergrid/locks/__init__.py
watergrid/metrics/ConsoleMetricsExporter.py
watergrid/metrics/ElasticAPMMetricsExporter.py
watergrid/metrics/MetricsExporter.py
watergrid/metrics/MetricsStore.py
watergrid/metrics/__init__.py
watergrid/pipelines/__init__.py
watergrid/pipelines/ha_pipeline.py
watergrid/pipelines/pipeline.py
watergrid/pipelines/pipeline_verifier.py
watergrid/pipelines/standalone_pipeline.py
watergrid/steps/__init__.py
watergrid/steps/sequence.py
watergrid/steps/step.py
watergrid-1.1.1.dist-info/LICENSE
watergrid-1.1.1.dist-info/METADATA
watergrid-1.1.1.dist-info/WHEEL
watergrid-1.1.1.dist-info/top_level.txt
watergrid-1.1.1.dist-info/zip-safe
watergrid-1.1.1.dist-info/RECORD
