Metadata-Version: 2.1
Name: watergrid
Version: 1.1.1
Summary: Lightweight framework for building ETL pipelines.
Home-page: https://github.com/ARMmaster17/watergrid-python
Author: Joshua Zenn
Author-email: wordman05@gmail.com
License: MIT License
Keywords: etl
Platform: UNKNOWN
Classifier: Programming Language :: Python :: 3
Classifier: License :: OSI Approved :: MIT License
Classifier: Operating System :: OS Independent
Requires-Python: >=3.6
License-File: LICENSE
Requires-Dist: pycron (==3.0.0)
Provides-Extra: lock-redis
Requires-Dist: redis (==4.2.2) ; extra == 'lock-redis'
Provides-Extra: metrics-elasticsearch
Requires-Dist: elastic-apm (==6.9.1) ; extra == 'metrics-elasticsearch'
